cli/__init__.py
levels/__init__.py
levels/q1/raw/q1_readme.txt.html
levels/q1/raw/v1.files.json
levels/q1/raw/v1.files.yaml
levels/q1/readme_q1_the-cake-isnot-a-lie.md
levels/q1/src/solution.py
levels/q1/tests/q1-exp.test.mjs
levels/q1/tests/solutions_test.py
levels/q2/dont_get_volunteered.py
levels/q2/raw/knight-tour-solution-1.png
levels/q2/raw/knight-tour-solution-2.png
levels/q2/raw/q2_readme.txt.html
levels/q2/raw/v2.files.json
levels/q2/raw/v2.files.yaml
levels/q2/readme_q2_dont-get-volunteered.md
levels/q2/src/solutions.py
levels/q2/tests/solutions_bfs_test.py
hychan48_google_foobar_2023_q4-0.2.2.dist-info/LICENSE
hychan48_google_foobar_2023_q4-0.2.2.dist-info/METADATA
hychan48_google_foobar_2023_q4-0.2.2.dist-info/WHEEL
hychan48_google_foobar_2023_q4-0.2.2.dist-info/entry_points.txt
hychan48_google_foobar_2023_q4-0.2.2.dist-info/RECORD
